mydiscord/__init__.py
mydiscord/mydiscord.py
mydiscord-1.1.0.dist-info/METADATA
mydiscord-1.1.0.dist-info/WHEEL
mydiscord-1.1.0.dist-info/top_level.txt
mydiscord-1.1.0.dist-info/RECORD
