Metadata-Version: 2.1
Name: mydiscord
Version: 1.1.0
Summary: MyDiscord, Control your Discord client with Python.
Home-page: https://github.com/CantCode023/MyDiscord
Author: CantCode
Author-email: cantcode023@gmail.com
License: UNKNOWN
Platform: UNKNOWN
Classifier: Programming Language :: Python :: 3
Requires-Python: >=3.7
